tales/__init__.py
tales/auth.py
tales/errors.py
tales/player.py
tales/watchdog.py
tales-0.0.4.dist-info/LICENSE
tales-0.0.4.dist-info/METADATA
tales-0.0.4.dist-info/WHEEL
tales-0.0.4.dist-info/top_level.txt
tales-0.0.4.dist-info/RECORD
